flask_multiprocess_controller/__init__.py
flask_multiprocess_controller/controller.py
flask_multiprocess_controller/logger.py
flask_multiprocess_controller/resource.py
flask_multiprocess_controller/task.py
flask_multiprocess_controller/template.py
flask_multiprocess_controller/utils.py
Flask_Multiprocess_Controller-0.1.1.dist-info/LICENSE.md
Flask_Multiprocess_Controller-0.1.1.dist-info/METADATA
Flask_Multiprocess_Controller-0.1.1.dist-info/WHEEL
Flask_Multiprocess_Controller-0.1.1.dist-info/top_level.txt
Flask_Multiprocess_Controller-0.1.1.dist-info/RECORD
