Metadata-Version: 2.1
Name: Flask-Multiprocess-Controller
Version: 0.1.1
Summary: Flask extension that provides an easy-to-implement controller for multiprocessing tasking. It provides default functions such as task-queueing, health-check, status-check, manual-stop and process-safe logger.
Home-page: https://github.com/W-Yuhao/Flask-Multiprocess-Controller
Author: Yuhao Wang
Author-email: hotaro0724@gmail.com
Maintainer: Yuhao Wang
Maintainer-email: hotaro0724@gmail.com
License: BSD-3-Clause
Platform: any
Classifier: Environment :: Web Environment
Classifier: Intended Audience :: Developers
Classifier: License :: OSI Approved :: BSD License
Classifier: Operating System :: OS Independent
Classifier: Programming Language :: Python
Classifier: Programming Language :: Python :: 3
Classifier: Topic :: Software Development :: Libraries :: Python Modules
Requires-Python: >=3.7
Requires-Dist: Flask (~=1.1)
Requires-Dist: requests (~=2.25)
Requires-Dist: Werkzeug (~=1.0)
Requires-Dist: flask-restful (~=0.3)
